vloc/__init__.py
vloc/plugin/__init__.py
vloc/plugin/__selenium__/__info__.py
vloc/plugin/__selenium__/__selenium__.py
vloc_plugin_selenium-0.0.7.dist-info/LICENSE.txt
vloc_plugin_selenium-0.0.7.dist-info/METADATA
vloc_plugin_selenium-0.0.7.dist-info/WHEEL
vloc_plugin_selenium-0.0.7.dist-info/top_level.txt
vloc_plugin_selenium-0.0.7.dist-info/RECORD
