Metadata-Version: 2.1
Name: vloc_plugin_selenium
Version: 0.0.7
Summary: Plugin functions for vloc
Author-email: Lin Yeh <lin_yeh@outlook.com>
License: MIT
Project-URL: GitHub, https://github.com/linyeh1129/vloc_plugin_selenium
Keywords: ui aumomation,computer vision
Classifier: Programming Language :: Python :: 3
Requires-Python: >=3.10
License-File: LICENSE.txt
Requires-Dist: vloc-plugin
